su6/__about__.py
su6/__init__.py
su6/cli.py
su6/core.py
su6/plugins.py
su6/py.typed
su6-1.9.1.dist-info/METADATA
su6-1.9.1.dist-info/WHEEL
su6-1.9.1.dist-info/entry_points.txt
su6-1.9.1.dist-info/licenses/LICENSE.txt
su6-1.9.1.dist-info/RECORD
