Metadata-Version: 2.4
Name: su6
Version: 1.9.1
Summary: Python cli tool to use tools for some common code quality checks (opinionated)
Project-URL: Documentation, https://github.com/trialandsuccess/su6#readme
Project-URL: Issues, https://github.com/trialandsuccess/su6/issues
Project-URL: Source, https://github.com/trialandsuccess/su6
Author-email: Robin van der Noord <robinvandernoord@gmail.com>
License-Expression: MIT
License-File: LICENSE.txt
Classifier: Development Status :: 4 - Beta
Classifier: Programming Language :: Python
Classifier: Programming Language :: Python :: 3.10
Classifier: Programming Language :: Python :: 3.11
Classifier: Programming Language :: Python :: 3.12
Classifier: Programming Language :: Python :: Implementation :: CPython
Classifier: Programming Language :: Python :: Implementation :: PyPy
Requires-Python: >=3.10
Requires-Dist: configuraptor>=1.14
Requires-Dist: plumbum
Requires-Dist: typer<0.19,>=0.18
Provides-Extra: all
Requires-Dist: bandit; extra == 'all'
Requires-Dist: black; extra == 'all'
Requires-Dist: contextlib-chdir; (python_version < '3.11') and extra == 'all'
Requires-Dist: genbadge[coverage]; extra == 'all'
Requires-Dist: isort; extra == 'all'
Requires-Dist: mypy; extra == 'all'
Requires-Dist: pydocstyle; extra == 'all'
Requires-Dist: pytest; extra == 'all'
Requires-Dist: pytest-cov; extra == 'all'
Requires-Dist: ruff; extra == 'all'
Provides-Extra: bandit
Requires-Dist: bandit; extra == 'bandit'
Provides-Extra: black
Requires-Dist: black; extra == 'black'
Provides-Extra: dev
Requires-Dist: hatch; extra == 'dev'
Requires-Dist: python-semantic-release<8; extra == 'dev'
Requires-Dist: su6-plugin-demo; extra == 'dev'
Provides-Extra: isort
Requires-Dist: isort; extra == 'isort'
Provides-Extra: mypy
Requires-Dist: mypy; extra == 'mypy'
Provides-Extra: prettier
Requires-Dist: su6-plugin-prettier; extra == 'prettier'
Provides-Extra: pydocstyle
Requires-Dist: pydocstyle; extra == 'pydocstyle'
Provides-Extra: pytest
Requires-Dist: contextlib-chdir; (python_version < '3.11') and extra == 'pytest'
Requires-Dist: genbadge[coverage]; extra == 'pytest'
Requires-Dist: pytest; extra == 'pytest'
Requires-Dist: pytest-cov; extra == 'pytest'
Provides-Extra: ruff
Requires-Dist: ruff; extra == 'ruff'
Provides-Extra: svelte-check
Requires-Dist: su6-plugin-svelte-check; extra == 'svelte-check'
